python_movie_transformer/__init__.py
python_movie_transformer/ffmpeg/__init__.py
python_movie_transformer/ffmpeg/image_file.py
python_movie_transformer/ffmpeg/manipulater.py
python_movie_transformer/ffmpeg/options.py
python_movie_transformer-0.0.dev1.dist-info/DESCRIPTION.rst
python_movie_transformer-0.0.dev1.dist-info/METADATA
python_movie_transformer-0.0.dev1.dist-info/RECORD
python_movie_transformer-0.0.dev1.dist-info/WHEEL
python_movie_transformer-0.0.dev1.dist-info/entry_points.txt
python_movie_transformer-0.0.dev1.dist-info/metadata.json
python_movie_transformer-0.0.dev1.dist-info/top_level.txt
