Metadata-Version: 2.0
Name: python-movie-transformer
Version: 0.0.dev1
Summary: Movie file filtering package wrapping ffmpy
Home-page: https://github.com/Fufuhu/python_movie_transcoder
Author: e238058r
Author-email: e238058r@hotmail.co.jp
License: MIT
Platform: UNKNOWN
Classifier: Programming Language :: Python :: 3.5
Classifier: License :: OSI Approved :: MIT License
Requires-Dist: ffmpy
